{"suburb": "Avoca Beach", "region": "Central Coast", "postcode": 2251, "slug": "avoca-beach", "region_slug": "central-coast", "generated_at": "2026-05-16T15:11:29Z", "available_types": ["All", "HOUSE"], "by_type": {"All": {"tiles": {"sales_count": {"value": 0, "label": "Sales This Week", "window": null, "sample": 78, "is_caution": true}, "median": {"value": 1697500, "label": "Median price (52-week)", "window": "52-week", "is_sqm": false, "sample": 78, "is_caution": true}, "avg": {"value": 1906929, "label": "Avg sale price (52-week)", "window": "52-week", "is_sqm": false, "sample": 78, "is_caution": true}}, "chart": {"x_label": "Year", "y_left_label": "Median price ($)", "y_right_label": "Sales volume", "primary_field": "median_price", "data": [{"year": 2001, "sales_count": 160, "median_price": 348750, "avg_price": 409136, "median_sqm": 410.58, "avg_sqm": 477.21}, {"year": 2002, "sales_count": 196, "median_price": 369500, "avg_price": 423724, "median_sqm": 430.84, "avg_sqm": 511.23}, {"year": 2003, "sales_count": 132, "median_price": 502500, "avg_price": 633361, "median_sqm": 604.65, "avg_sqm": 761.29}, {"year": 2004, "sales_count": 106, "median_price": 625000, "avg_price": 703108, "median_sqm": 713.44, "avg_sqm": 947.01}, {"year": 2005, "sales_count": 117, "median_price": 543000, "avg_price": 671872, "median_sqm": 648.28, "avg_sqm": 867.19}, {"year": 2006, "sales_count": 122, "median_price": 565000, "avg_price": 808883, "median_sqm": 693.47, "avg_sqm": 997.97}, {"year": 2007, "sales_count": 130, "median_price": 550000, "avg_price": 799035, "median_sqm": 668.88, "avg_sqm": 957.82}, {"year": 2008, "sales_count": 126, "median_price": 511000, "avg_price": 729308, "median_sqm": 625.17, "avg_sqm": 854.53}, {"year": 2009, "sales_count": 125, "median_price": 530000, "avg_price": 669517, "median_sqm": 640.51, "avg_sqm": 795.91}, {"year": 2011, "sales_count": 131, "median_price": 565000, "avg_price": 679672, "median_sqm": 642.07, "avg_sqm": 898.07}, {"year": 2012, "sales_count": 117, "median_price": 560000, "avg_price": 684155, "median_sqm": 694.65, "avg_sqm": 845.85}, {"year": 2013, "sales_count": 167, "median_price": 560000, "avg_price": 710237, "median_sqm": 715.03, "avg_sqm": 883.72}, {"year": 2014, "sales_count": 148, "median_price": 640000, "avg_price": 766892, "median_sqm": 836.27, "avg_sqm": 963.11}, {"year": 2015, "sales_count": 156, "median_price": 727500, "avg_price": 874348, "median_sqm": 1021.31, "avg_sqm": 1341.92}, {"year": 2016, "sales_count": 132, "median_price": 792500, "avg_price": 971745, "median_sqm": 963.22, "avg_sqm": 1262.58}, {"year": 2017, "sales_count": 143, "median_price": 900000, "avg_price": 1144038, "median_sqm": 1200.26, "avg_sqm": 1910.74}, {"year": 2018, "sales_count": 112, "median_price": 915000, "avg_price": 1166731, "median_sqm": 1241.74, "avg_sqm": 1903.45}, {"year": 2020, "sales_count": 138, "median_price": 1100000, "avg_price": 1310146, "median_sqm": 1489.38, "avg_sqm": 2281.27}, {"year": 2021, "sales_count": 136, "median_price": 1489000, "avg_price": 1777939, "median_sqm": 2212.53, "avg_sqm": 3282.23}, {"year": 2024, "sales_count": 101, "median_price": 1490000, "avg_price": 1716684, "median_sqm": 2112.06, "avg_sqm": 2766.99}], "ytd": null, "note": null}, "price_performance": {"is_sqm_basis": false, "3m": {"nominal": null, "pct": null, "note": "rolling quarter vs same quarter prior year"}, "12m": {"nominal": null, "pct": null}, "3y": {"nominal": 195000, "pct": 14.77}, "5y": {"nominal": 598000, "pct": 65.57}, "10y": {"nominal": 620000, "pct": 106.9}, "20y": {"nominal": 370000, "pct": 86.05}, "as_of": "2025-12-24"}, "narrative": ["101 settlements recorded in 2024 with a median price of $1,490,000", "Transaction volume slowed 26% vs 2021 (136 to 101 sales)", "10-year growth: +$620,000 (+106.9%) since 2014"], "data_coverage": {"first_year": 2001, "last_year": 2024, "years": 20}}, "HOUSE": {"tiles": {"sales_count": {"value": null, "label": "Sales This Week", "window": null, "sample": 53, "is_caution": true}, "median": {"value": 1800000, "label": "Median price (52-week)", "window": "52-week", "is_sqm": false, "sample": 53, "is_caution": true}, "avg": {"value": 1969104, "label": "Avg sale price (52-week)", "window": "52-week", "is_sqm": false, "sample": 53, "is_caution": true}}, "chart": {"x_label": "Year", "y_left_label": "Median price ($)", "y_right_label": "Sales volume", "primary_field": "median_price", "data": [{"year": 2001, "sales_count": 112, "median_price": 345000, "avg_price": 393422, "median_sqm": 414.82, "avg_sqm": 457.3}, {"year": 2002, "sales_count": 142, "median_price": 369500, "avg_price": 402052, "median_sqm": 434.25, "avg_sqm": 522.08}, {"year": 2013, "sales_count": 104, "median_price": 610000, "avg_price": 749486, "median_sqm": 736.06, "avg_sqm": 904.82}, {"year": 2014, "sales_count": 101, "median_price": 670000, "avg_price": 823723, "median_sqm": 838.04, "avg_sqm": 969.02}, {"year": 2015, "sales_count": 100, "median_price": 792500, "avg_price": 958507, "median_sqm": 1006.71, "avg_sqm": 1185.15}, {"year": 2020, "sales_count": 102, "median_price": 1145000, "avg_price": 1356148, "median_sqm": 1385.58, "avg_sqm": 1833.21}], "ytd": null, "note": null}, "price_performance": {"is_sqm_basis": false, "3m": {"nominal": null, "pct": null, "note": "rolling quarter vs same quarter prior year"}, "12m": {"nominal": null, "pct": null}, "3y": {"nominal": 119000, "pct": 8.04}, "5y": {"nominal": 622500, "pct": 63.68}, "10y": {"nominal": 687000, "pct": 116.44}, "20y": {"nominal": 410000, "pct": 95.35}, "as_of": "2025-12-24"}, "narrative": ["102 settlements recorded in 2020 with a median price of $1,145,000", "Median price up 44.5% vs 2015", "10-year growth: +$687,000 (+116.4%) since 2010"], "data_coverage": {"first_year": 2001, "last_year": 2020, "years": 6}}}}