{"suburb": "Potts Point", "region": "Eastern Suburbs", "postcode": 2011, "slug": "potts-point", "region_slug": "eastern-suburbs", "generated_at": "2026-05-21T12:26:23Z", "available_types": ["All", "House", "Unit/Apartment", "Retail", "Vacant Land", "Office", "OTHER"], "zone_available_types": {"Business": ["All", "House", "Retail", "Vacant Land", "OTHER"], "R1": ["All", "House", "Unit/Apartment", "Vacant Land"], "R2": ["All", "House", "Unit/Apartment", "Retail", "Vacant Land", "Office", "OTHER"]}, "by_type": {"All": {"tiles": {"sales_count": {"value": 0, "label": "Sales This Week", "window": null, "sample": 51, "is_caution": false}, "median": {"value": 920000, "label": "Median price (12-week)", "window": "12-week", "is_sqm": false, "sample": 51, "is_caution": false}, "avg": {"value": null, "label": "Median price/sqm (12-week)", "window": "12-week", "is_sqm": true, "sample": 51, "is_caution": false}}, "chart": {"x_label": "Year", "y_left_label": "Median price ($)", "y_right_label": "Sales volume", "primary_field": "median_price", "data": [{"year": 1999, "sales_count": 1, "median_price": 5000000, "avg_price": 5000000, "median_sqm": 5101.0, "avg_sqm": 5101.0}, {"year": 2000, "sales_count": 18, "median_price": 314500, "avg_price": 841511, "median_sqm": 3077.41, "avg_sqm": 3077.41}, {"year": 2001, "sales_count": 260, "median_price": 285000, "avg_price": 466914, "median_sqm": 6257.29, "avg_sqm": 6317.08}, {"year": 2002, "sales_count": 472, "median_price": 451000, "avg_price": 675277, "median_sqm": 9364.41, "avg_sqm": 8568.47}, {"year": 2003, "sales_count": 129, "median_price": 529000, "avg_price": 927156, "median_sqm": 13088.56, "avg_sqm": 13088.56}, {"year": 2004, "sales_count": 285, "median_price": 450000, "avg_price": 933280, "median_sqm": null, "avg_sqm": null}, {"year": 2005, "sales_count": 233, "median_price": 409000, "avg_price": 871321, "median_sqm": 10090.92, "avg_sqm": 10090.92}, {"year": 2006, "sales_count": 257, "median_price": 405000, "avg_price": 944749, "median_sqm": 12302.28, "avg_sqm": 13778.57}, {"year": 2007, "sales_count": 419, "median_price": 415000, "avg_price": 838660, "median_sqm": 9572.9, "avg_sqm": 9992.76}, {"year": 2008, "sales_count": 339, "median_price": 367500, "avg_price": 685855, "median_sqm": 21543.99, "avg_sqm": 19166.39}, {"year": 2009, "sales_count": 380, "median_price": 380000, "avg_price": 619578, "median_sqm": 8963.09, "avg_sqm": 12760.15}, {"year": 2010, "sales_count": 473, "median_price": 474000, "avg_price": 661978, "median_sqm": 8234.52, "avg_sqm": 9127.24}, {"year": 2011, "sales_count": 305, "median_price": 455000, "avg_price": 824913, "median_sqm": 10588.75, "avg_sqm": 12991.0}, {"year": 2012, "sales_count": 320, "median_price": 582500, "avg_price": 1034181, "median_sqm": 10575.65, "avg_sqm": 12812.54}, {"year": 2013, "sales_count": 312, "median_price": 570000, "avg_price": 977535, "median_sqm": 11436.78, "avg_sqm": 13515.48}, {"year": 2014, "sales_count": 289, "median_price": 610000, "avg_price": 1032121, "median_sqm": 11758.25, "avg_sqm": 13946.36}, {"year": 2015, "sales_count": 354, "median_price": 810625, "avg_price": 1917297, "median_sqm": 13784.13, "avg_sqm": 17462.21}, {"year": 2016, "sales_count": 285, "median_price": 955000, "avg_price": 1435652, "median_sqm": 17307.69, "avg_sqm": 17838.91}, {"year": 2017, "sales_count": 242, "median_price": 755000, "avg_price": 1507441, "median_sqm": 16652.79, "avg_sqm": 17213.05}, {"year": 2018, "sales_count": 178, "median_price": 847500, "avg_price": 1699767, "median_sqm": 16396.23, "avg_sqm": 18414.51}, {"year": 2019, "sales_count": 221, "median_price": 820000, "avg_price": 1519960, "median_sqm": 16000.0, "avg_sqm": 17290.83}, {"year": 2020, "sales_count": 193, "median_price": 870000, "avg_price": 1620730, "median_sqm": 16666.67, "avg_sqm": 18938.95}, {"year": 2021, "sales_count": 327, "median_price": 900000, "avg_price": 1654180, "median_sqm": 17936.51, "avg_sqm": 20387.03}, {"year": 2022, "sales_count": 263, "median_price": 940692, "avg_price": 1946905, "median_sqm": 15352.93, "avg_sqm": 17723.03}, {"year": 2023, "sales_count": 283, "median_price": 934500, "avg_price": 1597020, "median_sqm": 16878.28, "avg_sqm": 20298.95}, {"year": 2024, "sales_count": 324, "median_price": 729250, "avg_price": 1225812, "median_sqm": 15623.97, "avg_sqm": 18119.41}, {"year": 2025, "sales_count": 233, "median_price": 879000, "avg_price": 1340579, "median_sqm": 13587.69, "avg_sqm": 15751.45}], "ytd": null, "note": null}, "price_performance": {"is_sqm_basis": false, "3m": {"nominal": 68250, "pct": 8.01, "note": "rolling quarter vs same quarter prior year"}, "12m": {"nominal": 150000, "pct": 19.48}, "3y": {"nominal": -292644, "pct": -24.13}, "5y": {"nominal": -61500, "pct": -6.27}, "10y": {"nominal": -140000, "pct": -13.21}, "20y": {"nominal": 511000, "pct": 124.94}, "as_of": "2025-12-24"}, "narrative": ["233 settlements recorded in 2025 with a median price of $879,000", "Transaction volume slowed 28% vs 2024 (324 to 233 sales)", "10-year decline: $-140,000 (-13.2%) since 2015"], "available_zones": ["Business", "R1", "R2"], "by_zone": {"Business": {"tiles": {"sales_count": {"value": 0, "label": "Sales This Week", "window": null, "sample": 1, "is_caution": false}, "median": {"value": 3450000, "label": "Median price (16-week)", "window": "16-week", "is_sqm": false, "sample": 1, "is_caution": false}, "avg": {"value": null, "label": "Median price/sqm (16-week)", "window": "16-week", "is_sqm": true, "sample": 1, "is_caution": false}}, "chart": {"x_label": "Year", "y_left_label": "Median price ($)", "y_right_label": "Sales volume", "primary_field": "median_price", "data": [{"year": 2000, "sales_count": 1, "median_price": 2200000, "avg_price": 2200000, "median_sqm": 4380.72, "avg_sqm": 4380.72}, {"year": 2001, "sales_count": 4, "median_price": 2067500, "avg_price": 1865000, "median_sqm": 6607.55, "avg_sqm": 6607.55}, {"year": 2002, "sales_count": 2, "median_price": 2435000, "avg_price": 2435000, "median_sqm": 10017.65, "avg_sqm": 10017.65}, {"year": 2003, "sales_count": 1, "median_price": 4850000, "avg_price": 4850000, "median_sqm": 12597.4, "avg_sqm": 12597.4}, {"year": 2004, "sales_count": 1, "median_price": 1500000, "avg_price": 1500000, "median_sqm": null, "avg_sqm": null}, {"year": 2005, "sales_count": 1, "median_price": 3100000, "avg_price": 3100000, "median_sqm": 15712.11, "avg_sqm": 15712.11}, {"year": 2006, "sales_count": 9, "median_price": 6545000, "avg_price": 6349444, "median_sqm": 15695.07, "avg_sqm": 14905.25}, {"year": 2007, "sales_count": 4, "median_price": 2225000, "avg_price": 2737500, "median_sqm": 11347.9, "avg_sqm": 13145.3}, {"year": 2008, "sales_count": 3, "median_price": 6000000, "avg_price": 4850000, "median_sqm": 21543.99, "avg_sqm": 19166.39}, {"year": 2009, "sales_count": 7, "median_price": 1875000, "avg_price": 1875236, "median_sqm": 11859.58, "avg_sqm": 13124.42}, {"year": 2010, "sales_count": 4, "median_price": 1750000, "avg_price": 1969375, "median_sqm": 9117.26, "avg_sqm": 9094.79}, {"year": 2011, "sales_count": 7, "median_price": 3000000, "avg_price": 4501429, "median_sqm": 12978.61, "avg_sqm": 19135.09}, {"year": 2012, "sales_count": 7, "median_price": 6200000, "avg_price": 12054286, "median_sqm": 9272.73, "avg_sqm": 20126.12}, {"year": 2013, "sales_count": 6, "median_price": 856750, "avg_price": 963083, "median_sqm": 15057.12, "avg_sqm": 14505.17}, {"year": 2014, "sales_count": 12, "median_price": 3475000, "avg_price": 3982083, "median_sqm": 12584.17, "avg_sqm": 13274.62}, {"year": 2015, "sales_count": 13, "median_price": 8000000, "avg_price": 19934615, "median_sqm": 20448.24, "avg_sqm": 23917.15}, {"year": 2016, "sales_count": 4, "median_price": 7442500, "avg_price": 7646250, "median_sqm": 12618.61, "avg_sqm": 18826.14}, {"year": 2017, "sales_count": 7, "median_price": 4000000, "avg_price": 6839286, "median_sqm": 16924.21, "avg_sqm": 17585.01}, {"year": 2018, "sales_count": 6, "median_price": 5066000, "avg_price": 8438528, "median_sqm": 19943.33, "avg_sqm": 23272.68}, {"year": 2019, "sales_count": 5, "median_price": 8300000, "avg_price": 7680000, "median_sqm": 30294.89, "avg_sqm": 29290.3}, {"year": 2020, "sales_count": 5, "median_price": 6500000, "avg_price": 5523000, "median_sqm": 18571.43, "avg_sqm": 22710.48}, {"year": 2021, "sales_count": 14, "median_price": 5725000, "avg_price": 7141429, "median_sqm": 24824.4, "avg_sqm": 28438.04}, {"year": 2022, "sales_count": 6, "median_price": 3500000, "avg_price": 7549667, "median_sqm": 17724.43, "avg_sqm": 19017.13}, {"year": 2023, "sales_count": 3, "median_price": 5800000, "avg_price": 6483333, "median_sqm": 25777.78, "avg_sqm": 32228.92}, {"year": 2024, "sales_count": 6, "median_price": 3810000, "avg_price": 8395000, "median_sqm": 22911.89, "avg_sqm": 23872.26}, {"year": 2025, "sales_count": 1, "median_price": 3450000, "avg_price": 3450000, "median_sqm": 22727.27, "avg_sqm": 22727.27}], "ytd": null, "note": null}, "price_performance": {"is_sqm_basis": false, "3m": {"nominal": null, "pct": null, "note": "rolling quarter vs same quarter prior year"}, "12m": {"nominal": -3750000, "pct": -52.08}, "3y": {"nominal": -1350000, "pct": -28.12}, "5y": {"nominal": null, "pct": null}, "10y": {"nominal": -14300000, "pct": -80.56}, "20y": {"nominal": null, "pct": null}, "as_of": "2025-12-24"}}, "R1": {"tiles": {"sales_count": {"value": 0, "label": "Sales This Week", "window": null, "sample": 5, "is_caution": false}, "median": {"value": 2800000, "label": "Median price (12-week)", "window": "12-week", "is_sqm": false, "sample": 5, "is_caution": false}, "avg": {"value": null, "label": "Median price/sqm (12-week)", "window": "12-week", "is_sqm": true, "sample": 5, "is_caution": false}}, "chart": {"x_label": "Year", "y_left_label": "Median price ($)", "y_right_label": "Sales volume", "primary_field": "median_price", "data": [{"year": 2012, "sales_count": 2, "median_price": 3630000, "avg_price": 3630000, "median_sqm": 13867.99, "avg_sqm": 13867.99}, {"year": 2013, "sales_count": 4, "median_price": 1937500, "avg_price": 4338750, "median_sqm": 9207.18, "avg_sqm": 21145.82}, {"year": 2014, "sales_count": 5, "median_price": 3200000, "avg_price": 3362000, "median_sqm": 18198.36, "avg_sqm": 16891.16}, {"year": 2015, "sales_count": 10, "median_price": 2225000, "avg_price": 2597500, "median_sqm": 15281.08, "avg_sqm": 14225.45}, {"year": 2016, "sales_count": 6, "median_price": 4675000, "avg_price": 4300000, "median_sqm": 25675.58, "avg_sqm": 26274.15}, {"year": 2017, "sales_count": 4, "median_price": 2925000, "avg_price": 2898750, "median_sqm": 22706.08, "avg_sqm": 17852.68}, {"year": 2018, "sales_count": 5, "median_price": 3270000, "avg_price": 3849200, "median_sqm": 21754.39, "avg_sqm": 20737.46}, {"year": 2019, "sales_count": 5, "median_price": 4700000, "avg_price": 10130000, "median_sqm": 26566.69, "avg_sqm": 23465.48}, {"year": 2020, "sales_count": 7, "median_price": 4000000, "avg_price": 4763526, "median_sqm": 19379.84, "avg_sqm": 20033.4}, {"year": 2021, "sales_count": 4, "median_price": 5095000, "avg_price": 4555000, "median_sqm": 29581.4, "avg_sqm": 30448.33}, {"year": 2022, "sales_count": 6, "median_price": 6500000, "avg_price": 10775000, "median_sqm": 25870.62, "avg_sqm": 26630.15}, {"year": 2023, "sales_count": 8, "median_price": 2690000, "avg_price": 7334625, "median_sqm": 19066.81, "avg_sqm": 26296.21}, {"year": 2024, "sales_count": 3, "median_price": 8600000, "avg_price": 6920000, "median_sqm": 32379.52, "avg_sqm": 31682.13}, {"year": 2025, "sales_count": 5, "median_price": 2800000, "avg_price": 3670000, "median_sqm": 21084.34, "avg_sqm": 22787.0}], "ytd": null, "note": null}, "price_performance": {"is_sqm_basis": false, "3m": {"nominal": null, "pct": null, "note": "rolling quarter vs same quarter prior year"}, "12m": {"nominal": null, "pct": null}, "3y": {"nominal": -6200000, "pct": -68.89}, "5y": {"nominal": -3195000, "pct": -53.29}, "10y": {"nominal": -2550000, "pct": -47.66}, "20y": {"nominal": null, "pct": null}, "as_of": "2025-12-24"}}, "R2": {"tiles": {"sales_count": {"value": 0, "label": "Sales This Week", "window": null, "sample": 0, "is_caution": false}, "median": {"value": null, "label": "Median price (52-week)", "window": "52-week", "is_sqm": false, "sample": 0, "is_caution": false}, "avg": {"value": null, "label": "Median price/sqm (52-week)", "window": "52-week", "is_sqm": true, "sample": 0, "is_caution": false}}, "chart": {"x_label": "Year", "y_left_label": "Median price ($)", "y_right_label": "Sales volume", "primary_field": "median_price", "data": [{"year": 2001, "sales_count": 9, "median_price": 1100000, "avg_price": 1373667, "median_sqm": 6257.29, "avg_sqm": 6244.47}, {"year": 2002, "sales_count": 4, "median_price": 1277500, "avg_price": 1218125, "median_sqm": 7642.97, "avg_sqm": 7602.34}, {"year": 2004, "sales_count": 2, "median_price": 1150500, "avg_price": 1150500, "median_sqm": null, "avg_sqm": null}, {"year": 2005, "sales_count": 3, "median_price": 1095000, "avg_price": 1015000, "median_sqm": 4469.73, "avg_sqm": 4469.73}, {"year": 2006, "sales_count": 3, "median_price": 867000, "avg_price": 1230667, "median_sqm": 8708.5, "avg_sqm": 8708.5}, {"year": 2007, "sales_count": 13, "median_price": 875000, "avg_price": 2438077, "median_sqm": 7532.53, "avg_sqm": 9082.91}, {"year": 2009, "sales_count": 9, "median_price": 1280000, "avg_price": 2973178, "median_sqm": 8567.66, "avg_sqm": 7475.5}, {"year": 2010, "sales_count": 5, "median_price": 1065000, "avg_price": 1744800, "median_sqm": 9906.98, "avg_sqm": 8642.38}, {"year": 2011, "sales_count": 5, "median_price": 2165000, "avg_price": 4278000, "median_sqm": 10588.75, "avg_sqm": 11584.65}, {"year": 2012, "sales_count": 5, "median_price": 2450000, "avg_price": 2370000, "median_sqm": 16139.66, "avg_sqm": 13528.84}], "ytd": null, "note": null}, "price_performance": {"is_sqm_basis": false, "3m": {"nominal": null, "pct": null, "note": "rolling quarter vs same quarter prior year"}, "12m": {"nominal": null, "pct": null}, "3y": {"nominal": null, "pct": null}, "5y": {"nominal": null, "pct": null}, "10y": {"nominal": null, "pct": null}, "20y": {"nominal": null, "pct": null}, "as_of": "2025-12-24"}}}, "data_coverage": {"first_year": 1999, "last_year": 2025, "years": 27}}, "House": {"tiles": {"sales_count": {"value": 0, "label": "Sales This Week", "window": null, "sample": 50, "is_caution": false}, "median": {"value": 921000, "label": "Median price (12-week)", "window": "12-week", "is_sqm": false, "sample": 50, "is_caution": false}, "avg": {"value": null, "label": "Median price/sqm (12-week)", "window": "12-week", "is_sqm": true, "sample": 50, "is_caution": false}}, "chart": {"x_label": "Year", "y_left_label": "Median price ($)", "y_right_label": "Sales volume", "primary_field": "median_price", "data": [{"year": 2000, "sales_count": 7, "median_price": 313000, "avg_price": 544571, "median_sqm": null, "avg_sqm": null}, {"year": 2001, "sales_count": 154, "median_price": 297000, "avg_price": 478769, "median_sqm": 7753.26, "avg_sqm": 7565.85}, {"year": 2002, "sales_count": 429, "median_price": 465000, "avg_price": 687689, "median_sqm": 9364.41, "avg_sqm": 8498.04}, {"year": 2003, "sales_count": 122, "median_price": 529000, "avg_price": 878417, "median_sqm": null, "avg_sqm": null}, {"year": 2004, "sales_count": 259, "median_price": 450000, "avg_price": 848385, "median_sqm": null, "avg_sqm": null}, {"year": 2005, "sales_count": 211, "median_price": 409000, "avg_price": 822483, "median_sqm": 4469.73, "avg_sqm": 4469.73}, {"year": 2006, "sales_count": 233, "median_price": 395000, "avg_price": 823522, "median_sqm": 11859.32, "avg_sqm": 9451.94}, {"year": 2007, "sales_count": 366, "median_price": 405000, "avg_price": 783015, "median_sqm": 7895.09, "avg_sqm": 9862.29}, {"year": 2008, "sales_count": 310, "median_price": 370000, "avg_price": 574629, "median_sqm": 23647.5, "avg_sqm": 23647.5}, {"year": 2009, "sales_count": 337, "median_price": 375000, "avg_price": 607560, "median_sqm": 8963.09, "avg_sqm": 13925.14}, {"year": 2010, "sales_count": 385, "median_price": 467500, "avg_price": 628018, "median_sqm": 10223.1, "avg_sqm": 10192.8}, {"year": 2011, "sales_count": 248, "median_price": 449250, "avg_price": 685288, "median_sqm": 9847.46, "avg_sqm": 9545.63}, {"year": 2012, "sales_count": 245, "median_price": 585000, "avg_price": 717862, "median_sqm": 10526.3, "avg_sqm": 10727.34}, {"year": 2013, "sales_count": 274, "median_price": 570000, "avg_price": 939641, "median_sqm": 11436.78, "avg_sqm": 13554.88}, {"year": 2014, "sales_count": 251, "median_price": 610000, "avg_price": 896847, "median_sqm": 11758.25, "avg_sqm": 13055.96}, {"year": 2015, "sales_count": 312, "median_price": 806000, "avg_price": 1273077, "median_sqm": 13553.11, "avg_sqm": 14027.3}, {"year": 2016, "sales_count": 251, "median_price": 980000, "avg_price": 1419469, "median_sqm": 17783.02, "avg_sqm": 18784.98}, {"year": 2017, "sales_count": 214, "median_price": 737500, "avg_price": 1346577, "median_sqm": 16783.22, "avg_sqm": 17615.08}, {"year": 2018, "sales_count": 160, "median_price": 835000, "avg_price": 1584397, "median_sqm": 17548.04, "avg_sqm": 18946.35}, {"year": 2019, "sales_count": 203, "median_price": 795000, "avg_price": 1470295, "median_sqm": 16000.0, "avg_sqm": 17194.97}, {"year": 2020, "sales_count": 177, "median_price": 870000, "avg_price": 1567372, "median_sqm": 16256.59, "avg_sqm": 18169.94}, {"year": 2021, "sales_count": 305, "median_price": 900000, "avg_price": 1544979, "median_sqm": 17936.51, "avg_sqm": 20925.84}, {"year": 2022, "sales_count": 243, "median_price": 950000, "avg_price": 1705963, "median_sqm": 15555.56, "avg_sqm": 17638.81}, {"year": 2023, "sales_count": 274, "median_price": 936000, "avg_price": 1628520, "median_sqm": 16929.82, "avg_sqm": 20812.27}, {"year": 2024, "sales_count": 239, "median_price": 850000, "avg_price": 1343168, "median_sqm": 15573.77, "avg_sqm": 18167.23}, {"year": 2025, "sales_count": 227, "median_price": 883200, "avg_price": 1317936, "median_sqm": 14144.74, "avg_sqm": 16096.78}], "ytd": null, "note": null}, "price_performance": {"is_sqm_basis": false, "3m": {"nominal": 68250, "pct": 8.01, "note": "rolling quarter vs same quarter prior year"}, "12m": {"nominal": 142500, "pct": 18.33}, "3y": {"nominal": -280000, "pct": -23.33}, "5y": {"nominal": 23500, "pct": 2.62}, "10y": {"nominal": -150000, "pct": -14.02}, "20y": {"nominal": 570000, "pct": 162.86}, "as_of": "2025-12-24"}, "narrative": ["227 settlements recorded in 2025 with a median price of $883,200", "Median price up 3.9% vs 2024", "10-year decline: $-150,000 (-14.0%) since 2015"], "available_zones": ["Business", "R1", "R2"], "by_zone": {"Business": {"tiles": {"sales_count": {"value": 0, "label": "Sales This Week", "window": null, "sample": 1, "is_caution": false}, "median": {"value": 3450000, "label": "Median price (16-week)", "window": "16-week", "is_sqm": false, "sample": 1, "is_caution": false}, "avg": {"value": null, "label": "Median price/sqm (16-week)", "window": "16-week", "is_sqm": true, "sample": 1, "is_caution": false}}, "chart": {"x_label": "Year", "y_left_label": "Median price ($)", "y_right_label": "Sales volume", "primary_field": "median_price", "data": [{"year": 2001, "sales_count": 1, "median_price": 2500000, "avg_price": 2500000, "median_sqm": 10137.88, "avg_sqm": 10137.88}, {"year": 2002, "sales_count": 1, "median_price": 820000, "avg_price": 820000, "median_sqm": 10330.06, "avg_sqm": 10330.06}, {"year": 2006, "sales_count": 4, "median_price": 4550000, "avg_price": 4850000, "median_sqm": 9484.48, "avg_sqm": 8850.1}, {"year": 2007, "sales_count": 1, "median_price": 5200000, "avg_price": 5200000, "median_sqm": 20312.5, "avg_sqm": 20312.5}, {"year": 2008, "sales_count": 1, "median_price": 6950000, "avg_price": 6950000, "median_sqm": 23647.5, "avg_sqm": 23647.5}, {"year": 2009, "sales_count": 4, "median_price": 1192500, "avg_price": 1546250, "median_sqm": 10411.33, "avg_sqm": 10803.58}, {"year": 2010, "sales_count": 1, "median_price": 605000, "avg_price": 605000, "median_sqm": 10632.69, "avg_sqm": 10632.69}, {"year": 2011, "sales_count": 2, "median_price": 3820000, "avg_price": 3820000, "median_sqm": 10242.59, "avg_sqm": 10242.59}, {"year": 2013, "sales_count": 3, "median_price": 860000, "avg_price": 1221167, "median_sqm": 15000.0, "avg_sqm": 12861.71}, {"year": 2014, "sales_count": 7, "median_price": 2850000, "avg_price": 3916429, "median_sqm": 11716.46, "avg_sqm": 12455.59}, {"year": 2015, "sales_count": 1, "median_price": 3700000, "avg_price": 3700000, "median_sqm": 13553.11, "avg_sqm": 13553.11}, {"year": 2016, "sales_count": 2, "median_price": 7850000, "avg_price": 7850000, "median_sqm": 25133.99, "avg_sqm": 25133.99}, {"year": 2017, "sales_count": 1, "median_price": 2725000, "avg_price": 2725000, "median_sqm": 17235.93, "avg_sqm": 17235.93}, {"year": 2018, "sales_count": 1, "median_price": 14699167, "avg_price": 14699167, "median_sqm": 43042.95, "avg_sqm": 43042.95}, {"year": 2019, "sales_count": 3, "median_price": 6400000, "avg_price": 6866667, "median_sqm": 32653.06, "avg_sqm": 29741.49}, {"year": 2021, "sales_count": 10, "median_price": 5500000, "avg_price": 5958000, "median_sqm": 29207.34, "avg_sqm": 32679.22}, {"year": 2022, "sales_count": 3, "median_price": 1438000, "avg_price": 2532667, "median_sqm": 20425.53, "avg_sqm": 16828.89}, {"year": 2023, "sales_count": 3, "median_price": 5800000, "avg_price": 6483333, "median_sqm": 25777.78, "avg_sqm": 32228.92}, {"year": 2024, "sales_count": 4, "median_price": 3810000, "avg_price": 5292500, "median_sqm": 24493.78, "avg_sqm": 25181.35}, {"year": 2025, "sales_count": 1, "median_price": 3450000, "avg_price": 3450000, "median_sqm": 22727.27, "avg_sqm": 22727.27}], "ytd": null, "note": null}, "price_performance": {"is_sqm_basis": false, "3m": {"nominal": null, "pct": null, "note": "rolling quarter vs same quarter prior year"}, "12m": {"nominal": -3750000, "pct": -52.08}, "3y": {"nominal": -1350000, "pct": -28.12}, "5y": {"nominal": null, "pct": null}, "10y": {"nominal": null, "pct": null}, "20y": {"nominal": null, "pct": null}, "as_of": "2025-12-24"}}, "R1": {"tiles": {"sales_count": {"value": 0, "label": "Sales This Week", "window": null, "sample": 5, "is_caution": false}, "median": {"value": 2800000, "label": "Median price (12-week)", "window": "12-week", "is_sqm": false, "sample": 5, "is_caution": false}, "avg": {"value": null, "label": "Median price/sqm (12-week)", "window": "12-week", "is_sqm": true, "sample": 5, "is_caution": false}}, "chart": {"x_label": "Year", "y_left_label": "Median price ($)", "y_right_label": "Sales volume", "primary_field": "median_price", "data": [{"year": 2012, "sales_count": 1, "median_price": 2760000, "avg_price": 2760000, "median_sqm": 9487.8, "avg_sqm": 9487.8}, {"year": 2013, "sales_count": 4, "median_price": 1937500, "avg_price": 4338750, "median_sqm": 9207.18, "avg_sqm": 21145.82}, {"year": 2014, "sales_count": 5, "median_price": 3200000, "avg_price": 3362000, "median_sqm": 18198.36, "avg_sqm": 16891.16}, {"year": 2015, "sales_count": 9, "median_price": 2700000, "avg_price": 2884444, "median_sqm": 16099.36, "avg_sqm": 15779.17}, {"year": 2016, "sales_count": 6, "median_price": 4675000, "avg_price": 4300000, "median_sqm": 25675.58, "avg_sqm": 26274.15}, {"year": 2017, "sales_count": 4, "median_price": 2925000, "avg_price": 2898750, "median_sqm": 22706.08, "avg_sqm": 17852.68}, {"year": 2018, "sales_count": 5, "median_price": 3270000, "avg_price": 3849200, "median_sqm": 21754.39, "avg_sqm": 20737.46}, {"year": 2019, "sales_count": 5, "median_price": 4700000, "avg_price": 10130000, "median_sqm": 26566.69, "avg_sqm": 23465.48}, {"year": 2020, "sales_count": 7, "median_price": 4000000, "avg_price": 4763526, "median_sqm": 19379.84, "avg_sqm": 20033.4}, {"year": 2021, "sales_count": 4, "median_price": 5095000, "avg_price": 4555000, "median_sqm": 29581.4, "avg_sqm": 30448.33}, {"year": 2022, "sales_count": 6, "median_price": 6500000, "avg_price": 10775000, "median_sqm": 25870.62, "avg_sqm": 26630.15}, {"year": 2023, "sales_count": 8, "median_price": 2690000, "avg_price": 7334625, "median_sqm": 19066.81, "avg_sqm": 26296.21}, {"year": 2024, "sales_count": 3, "median_price": 8600000, "avg_price": 6920000, "median_sqm": 32379.52, "avg_sqm": 31682.13}, {"year": 2025, "sales_count": 5, "median_price": 2800000, "avg_price": 3670000, "median_sqm": 21084.34, "avg_sqm": 22787.0}], "ytd": null, "note": null}, "price_performance": {"is_sqm_basis": false, "3m": {"nominal": null, "pct": null, "note": "rolling quarter vs same quarter prior year"}, "12m": {"nominal": null, "pct": null}, "3y": {"nominal": -6200000, "pct": -68.89}, "5y": {"nominal": -3195000, "pct": -53.29}, "10y": {"nominal": -2550000, "pct": -47.66}, "20y": {"nominal": null, "pct": null}, "as_of": "2025-12-24"}}, "R2": {"tiles": {"sales_count": {"value": 0, "label": "Sales This Week", "window": null, "sample": 0, "is_caution": false}, "median": {"value": null, "label": "Median price (52-week)", "window": "52-week", "is_sqm": false, "sample": 0, "is_caution": false}, "avg": {"value": null, "label": "Median price/sqm (52-week)", "window": "52-week", "is_sqm": true, "sample": 0, "is_caution": false}}, "chart": {"x_label": "Year", "y_left_label": "Median price ($)", "y_right_label": "Sales volume", "primary_field": "median_price", "data": [{"year": 2001, "sales_count": 5, "median_price": 1305000, "avg_price": 1210600, "median_sqm": 7115.59, "avg_sqm": 7051.45}, {"year": 2002, "sales_count": 3, "median_price": 1125000, "avg_price": 1147500, "median_sqm": 7582.03, "avg_sqm": 7582.03}, {"year": 2004, "sales_count": 1, "median_price": 461000, "avg_price": 461000, "median_sqm": null, "avg_sqm": null}, {"year": 2005, "sales_count": 3, "median_price": 1095000, "avg_price": 1015000, "median_sqm": 4469.73, "avg_sqm": 4469.73}, {"year": 2006, "sales_count": 2, "median_price": 1412500, "avg_price": 1412500, "median_sqm": 11859.32, "avg_sqm": 11859.32}, {"year": 2007, "sales_count": 13, "median_price": 875000, "avg_price": 2438077, "median_sqm": 7532.53, "avg_sqm": 9082.91}, {"year": 2009, "sales_count": 8, "median_price": 1615000, "avg_price": 3341625, "median_sqm": 8678.99, "avg_sqm": 8358.32}, {"year": 2010, "sales_count": 4, "median_price": 1177500, "avg_price": 2137250, "median_sqm": 10223.1, "avg_sqm": 10726.27}, {"year": 2011, "sales_count": 3, "median_price": 1840000, "avg_price": 1736667, "median_sqm": 10182.62, "avg_sqm": 10094.56}, {"year": 2012, "sales_count": 4, "median_price": 2125000, "avg_price": 1962500, "median_sqm": 13645.66, "avg_sqm": 12747.85}], "ytd": null, "note": null}, "price_performance": {"is_sqm_basis": false, "3m": {"nominal": null, "pct": null, "note": "rolling quarter vs same quarter prior year"}, "12m": {"nominal": null, "pct": null}, "3y": {"nominal": null, "pct": null}, "5y": {"nominal": null, "pct": null}, "10y": {"nominal": null, "pct": null}, "20y": {"nominal": null, "pct": null}, "as_of": "2025-12-24"}}}, "data_coverage": {"first_year": 2000, "last_year": 2025, "years": 26}}, "Unit/Apartment": {"tiles": {"sales_count": {"value": 0, "label": "Sales This Week", "window": null, "sample": 0, "is_caution": false}, "median": {"value": null, "label": "Median price (52-week)", "window": "52-week", "is_sqm": false, "sample": 0, "is_caution": false}, "avg": {"value": null, "label": "Median price/sqm (52-week)", "window": "52-week", "is_sqm": true, "sample": 0, "is_caution": false}}, "chart": {"x_label": "Year", "y_left_label": "Median price ($)", "y_right_label": "Sales volume", "primary_field": "median_price", "data": [{"year": 2000, "sales_count": 1, "median_price": 315000, "avg_price": 315000, "median_sqm": null, "avg_sqm": null}, {"year": 2001, "sales_count": 21, "median_price": 236000, "avg_price": 413601, "median_sqm": null, "avg_sqm": null}, {"year": 2002, "sales_count": 22, "median_price": 258500, "avg_price": 357748, "median_sqm": null, "avg_sqm": null}, {"year": 2003, "sales_count": 2, "median_price": 425000, "avg_price": 425000, "median_sqm": null, "avg_sqm": null}, {"year": 2004, "sales_count": 8, "median_price": 320000, "avg_price": 691250, "median_sqm": null, "avg_sqm": null}, {"year": 2005, "sales_count": 6, "median_price": 205000, "avg_price": 268333, "median_sqm": null, "avg_sqm": null}, {"year": 2006, "sales_count": 6, "median_price": 377500, "avg_price": 492667, "median_sqm": null, "avg_sqm": null}, {"year": 2007, "sales_count": 10, "median_price": 379000, "avg_price": 519268, "median_sqm": null, "avg_sqm": null}, {"year": 2008, "sales_count": 8, "median_price": 360000, "avg_price": 2338125, "median_sqm": null, "avg_sqm": null}, {"year": 2009, "sales_count": 3, "median_price": 362000, "avg_price": 367639, "median_sqm": null, "avg_sqm": null}, {"year": 2010, "sales_count": 13, "median_price": 325000, "avg_price": 478391, "median_sqm": null, "avg_sqm": null}, {"year": 2011, "sales_count": 14, "median_price": 475000, "avg_price": 611500, "median_sqm": null, "avg_sqm": null}, {"year": 2012, "sales_count": 24, "median_price": 560000, "avg_price": 731938, "median_sqm": 18248.18, "avg_sqm": 18248.18}, {"year": 2013, "sales_count": 15, "median_price": 785000, "avg_price": 2083767, "median_sqm": 5901.43, "avg_sqm": 5901.43}, {"year": 2014, "sales_count": 9, "median_price": 392500, "avg_price": 549878, "median_sqm": null, "avg_sqm": null}, {"year": 2015, "sales_count": 7, "median_price": 715000, "avg_price": 1002857, "median_sqm": null, "avg_sqm": null}, {"year": 2016, "sales_count": 2, "median_price": 720000, "avg_price": 720000, "median_sqm": null, "avg_sqm": null}, {"year": 2017, "sales_count": 1, "median_price": 1000000, "avg_price": 1000000, "median_sqm": null, "avg_sqm": null}], "ytd": null, "note": null}, "price_performance": {"is_sqm_basis": false, "3m": {"nominal": null, "pct": null, "note": "rolling quarter vs same quarter prior year"}, "12m": {"nominal": null, "pct": null}, "3y": {"nominal": null, "pct": null}, "5y": {"nominal": null, "pct": null}, "10y": {"nominal": null, "pct": null}, "20y": {"nominal": null, "pct": null}, "as_of": "2025-12-24"}, "narrative": ["1 settlements recorded in 2017 with a median price of $1,000,000", "Transaction volume slowed 50% vs 2016 (2 to 1 sales)"], "available_zones": ["R1", "R2"], "by_zone": {"R1": {"tiles": {"sales_count": {"value": 0, "label": "Sales This Week", "window": null, "sample": 0, "is_caution": false}, "median": {"value": null, "label": "Median price (52-week)", "window": "52-week", "is_sqm": false, "sample": 0, "is_caution": false}, "avg": {"value": null, "label": "Median price/sqm (52-week)", "window": "52-week", "is_sqm": true, "sample": 0, "is_caution": false}}, "chart": {"x_label": "Year", "y_left_label": "Median price ($)", "y_right_label": "Sales volume", "primary_field": "median_price", "data": [{"year": 2012, "sales_count": 1, "median_price": 4500000, "avg_price": 4500000, "median_sqm": 18248.18, "avg_sqm": 18248.18}], "ytd": null, "note": "1 year of qualifying data"}, "price_performance": {"is_sqm_basis": false, "3m": {"nominal": null, "pct": null, "note": "rolling quarter vs same quarter prior year"}, "12m": {"nominal": null, "pct": null}, "3y": {"nominal": null, "pct": null}, "5y": {"nominal": null, "pct": null}, "10y": {"nominal": null, "pct": null}, "20y": {"nominal": null, "pct": null}, "as_of": "2025-12-24"}}, "R2": {"tiles": {"sales_count": {"value": 0, "label": "Sales This Week", "window": null, "sample": 0, "is_caution": false}, "median": {"value": null, "label": "Median price (52-week)", "window": "52-week", "is_sqm": false, "sample": 0, "is_caution": false}, "avg": {"value": null, "label": "Median price/sqm (52-week)", "window": "52-week", "is_sqm": true, "sample": 0, "is_caution": false}}, "chart": {"x_label": "Year", "y_left_label": "Median price ($)", "y_right_label": "Sales volume", "primary_field": "median_price", "data": [{"year": 2001, "sales_count": 1, "median_price": 4000000, "avg_price": 4000000, "median_sqm": null, "avg_sqm": null}], "ytd": null, "note": "1 year of qualifying data"}, "price_performance": {"is_sqm_basis": false, "3m": {"nominal": null, "pct": null, "note": "rolling quarter vs same quarter prior year"}, "12m": {"nominal": null, "pct": null}, "3y": {"nominal": null, "pct": null}, "5y": {"nominal": null, "pct": null}, "10y": {"nominal": null, "pct": null}, "20y": {"nominal": null, "pct": null}, "as_of": "2025-12-24"}}}, "data_coverage": {"first_year": 2000, "last_year": 2017, "years": 18}}, "Retail": {"tiles": {"sales_count": {"value": 0, "label": "Sales This Week", "window": null, "sample": 1, "is_caution": false}, "median": {"value": 742500, "label": "Median price (24-week)", "window": "24-week", "is_sqm": false, "sample": 1, "is_caution": false}, "avg": {"value": null, "label": "Median price/sqm (24-week)", "window": "24-week", "is_sqm": true, "sample": 1, "is_caution": false}}, "chart": {"x_label": "Year", "y_left_label": "Median price ($)", "y_right_label": "Sales volume", "primary_field": "median_price", "data": [{"year": 2000, "sales_count": 1, "median_price": 2200000, "avg_price": 2200000, "median_sqm": 4380.72, "avg_sqm": 4380.72}, {"year": 2001, "sales_count": 5, "median_price": 1048000, "avg_price": 1206600, "median_sqm": null, "avg_sqm": null}, {"year": 2002, "sales_count": 5, "median_price": 435000, "avg_price": 1213600, "median_sqm": 9705.25, "avg_sqm": 9705.25}, {"year": 2003, "sales_count": 2, "median_price": 4767500, "avg_price": 4767500, "median_sqm": 13088.56, "avg_sqm": 13088.56}, {"year": 2004, "sales_count": 9, "median_price": 1500000, "avg_price": 4181456, "median_sqm": null, "avg_sqm": null}, {"year": 2005, "sales_count": 9, "median_price": 1700000, "avg_price": 2731833, "median_sqm": 15712.11, "avg_sqm": 15712.11}, {"year": 2006, "sales_count": 7, "median_price": 1780000, "avg_price": 4527857, "median_sqm": 22810.22, "avg_sqm": 22849.19}, {"year": 2007, "sales_count": 28, "median_price": 632500, "avg_price": 1897868, "median_sqm": 11347.9, "avg_sqm": 11347.9}, {"year": 2008, "sales_count": 13, "median_price": 317000, "avg_price": 1361444, "median_sqm": 16925.84, "avg_sqm": 16925.84}, {"year": 2009, "sales_count": 29, "median_price": 665000, "avg_price": 867452, "median_sqm": 11153.85, "avg_sqm": 12200.6}, {"year": 2010, "sales_count": 46, "median_price": 764500, "avg_price": 1147163, "median_sqm": 7647.06, "avg_sqm": 8001.29}, {"year": 2011, "sales_count": 26, "median_price": 627500, "avg_price": 1742792, "median_sqm": 12998.27, "avg_sqm": 17945.58}, {"year": 2012, "sales_count": 36, "median_price": 614000, "avg_price": 3664917, "median_sqm": 12055.72, "avg_sqm": 19691.95}, {"year": 2013, "sales_count": 19, "median_price": 300000, "avg_price": 626895, "median_sqm": 19435.54, "avg_sqm": 19435.54}, {"year": 2014, "sales_count": 24, "median_price": 1277500, "avg_price": 2778812, "median_sqm": 12592.59, "avg_sqm": 16562.96}, {"year": 2015, "sales_count": 27, "median_price": 1705000, "avg_price": 9822333, "median_sqm": 20448.24, "avg_sqm": 23036.67}, {"year": 2016, "sales_count": 24, "median_price": 762850, "avg_price": 1980362, "median_sqm": 12146.34, "avg_sqm": 11856.36}, {"year": 2017, "sales_count": 21, "median_price": 2300000, "avg_price": 3475629, "median_sqm": 15343.94, "avg_sqm": 16358.73}, {"year": 2018, "sales_count": 16, "median_price": 1570000, "avg_price": 3012500, "median_sqm": 14343.74, "avg_sqm": 18190.36}, {"year": 2019, "sales_count": 13, "median_price": 1600000, "avg_price": 2602020, "median_sqm": 27936.72, "avg_sqm": 27936.72}, {"year": 2020, "sales_count": 11, "median_price": 2150000, "avg_price": 2976455, "median_sqm": 18170.01, "avg_sqm": 21886.83}, {"year": 2021, "sales_count": 21, "median_price": 900000, "avg_price": 3301824, "median_sqm": 18100.4, "avg_sqm": 16525.55}, {"year": 2022, "sales_count": 15, "median_price": 1066000, "avg_price": 6218733, "median_sqm": 15023.33, "avg_sqm": 21205.37}, {"year": 2023, "sales_count": 7, "median_price": 500000, "avg_price": 671714, "median_sqm": 4385.96, "avg_sqm": 4385.96}, {"year": 2024, "sales_count": 84, "median_price": 418500, "avg_price": 902330, "median_sqm": 20439.63, "avg_sqm": 17689.05}, {"year": 2025, "sales_count": 5, "median_price": 742500, "avg_price": 2593700, "median_sqm": 8326.92, "avg_sqm": 8326.92}], "ytd": null, "note": null}, "price_performance": {"is_sqm_basis": false, "3m": {"nominal": null, "pct": null, "note": "rolling quarter vs same quarter prior year"}, "12m": {"nominal": null, "pct": null}, "3y": {"nominal": null, "pct": null}, "5y": {"nominal": null, "pct": null}, "10y": {"nominal": null, "pct": null}, "20y": {"nominal": null, "pct": null}, "as_of": "2025-12-24"}, "narrative": ["5 settlements recorded in 2025 with a median price of $742,500", "Transaction volume slowed 94% vs 2024 (84 to 5 sales)"], "available_zones": ["Business", "R2"], "by_zone": {"Business": {"tiles": {"sales_count": {"value": 0, "label": "Sales This Week", "window": null, "sample": 0, "is_caution": false}, "median": {"value": null, "label": "Median price (52-week)", "window": "52-week", "is_sqm": false, "sample": 0, "is_caution": false}, "avg": {"value": null, "label": "Median price/sqm (52-week)", "window": "52-week", "is_sqm": true, "sample": 0, "is_caution": false}}, "chart": {"x_label": "Year", "y_left_label": "Median price ($)", "y_right_label": "Sales volume", "primary_field": "median_price", "data": [{"year": 2000, "sales_count": 1, "median_price": 2200000, "avg_price": 2200000, "median_sqm": 4380.72, "avg_sqm": 4380.72}, {"year": 2001, "sales_count": 2, "median_price": 2067500, "avg_price": 2067500, "median_sqm": null, "avg_sqm": null}, {"year": 2002, "sales_count": 1, "median_price": 4050000, "avg_price": 4050000, "median_sqm": 9705.25, "avg_sqm": 9705.25}, {"year": 2003, "sales_count": 1, "median_price": 4850000, "avg_price": 4850000, "median_sqm": 12597.4, "avg_sqm": 12597.4}, {"year": 2004, "sales_count": 1, "median_price": 1500000, "avg_price": 1500000, "median_sqm": null, "avg_sqm": null}, {"year": 2005, "sales_count": 1, "median_price": 3100000, "avg_price": 3100000, "median_sqm": 15712.11, "avg_sqm": 15712.11}, {"year": 2006, "sales_count": 3, "median_price": 7500000, "avg_price": 9116667, "median_sqm": 22810.22, "avg_sqm": 22849.19}, {"year": 2007, "sales_count": 2, "median_price": 2225000, "avg_price": 2225000, "median_sqm": 11347.9, "avg_sqm": 11347.9}, {"year": 2008, "sales_count": 2, "median_price": 3800000, "avg_price": 3800000, "median_sqm": 16925.84, "avg_sqm": 16925.84}, {"year": 2009, "sales_count": 3, "median_price": 1891650, "avg_price": 2313883, "median_sqm": 13235.29, "avg_sqm": 16218.87}, {"year": 2010, "sales_count": 3, "median_price": 2250000, "avg_price": 2424167, "median_sqm": 8234.52, "avg_sqm": 8582.16}, {"year": 2011, "sales_count": 5, "median_price": 3000000, "avg_price": 4774000, "median_sqm": 13301.85, "avg_sqm": 23581.35}, {"year": 2012, "sales_count": 7, "median_price": 6200000, "avg_price": 12054286, "median_sqm": 9272.73, "avg_sqm": 20126.12}, {"year": 2013, "sales_count": 3, "median_price": 300000, "avg_price": 705000, "median_sqm": 19435.54, "avg_sqm": 19435.54}, {"year": 2014, "sales_count": 5, "median_price": 5200000, "avg_price": 4074000, "median_sqm": 13451.89, "avg_sqm": 14421.27}, {"year": 2015, "sales_count": 10, "median_price": 16875000, "avg_price": 24785000, "median_sqm": 25263.62, "avg_sqm": 24295.48}, {"year": 2016, "sales_count": 2, "median_price": 7442500, "avg_price": 7442500, "median_sqm": 12518.3, "avg_sqm": 12518.3}, {"year": 2017, "sales_count": 6, "median_price": 4500000, "avg_price": 7525000, "median_sqm": 16788.5, "avg_sqm": 17643.19}, {"year": 2018, "sales_count": 5, "median_price": 3150000, "avg_price": 7186400, "median_sqm": 15655.89, "avg_sqm": 19318.63}, {"year": 2019, "sales_count": 2, "median_price": 8900000, "avg_price": 8900000, "median_sqm": 27936.72, "avg_sqm": 27936.72}, {"year": 2020, "sales_count": 5, "median_price": 6500000, "avg_price": 5523000, "median_sqm": 18571.43, "avg_sqm": 22710.48}, {"year": 2021, "sales_count": 4, "median_price": 7985000, "avg_price": 10100000, "median_sqm": 20472.94, "avg_sqm": 17835.08}, {"year": 2022, "sales_count": 3, "median_price": 16500000, "avg_price": 12566667, "median_sqm": 15023.33, "avg_sqm": 21205.37}, {"year": 2024, "sales_count": 2, "median_price": 14600000, "avg_price": 14600000, "median_sqm": 21254.07, "avg_sqm": 21254.07}], "ytd": null, "note": null}, "price_performance": {"is_sqm_basis": false, "3m": {"nominal": null, "pct": null, "note": "rolling quarter vs same quarter prior year"}, "12m": {"nominal": null, "pct": null}, "3y": {"nominal": null, "pct": null}, "5y": {"nominal": null, "pct": null}, "10y": {"nominal": null, "pct": null}, "20y": {"nominal": null, "pct": null}, "as_of": "2025-12-24"}}, "R2": {"tiles": {"sales_count": {"value": 0, "label": "Sales This Week", "window": null, "sample": 0, "is_caution": false}, "median": {"value": null, "label": "Median price (52-week)", "window": "52-week", "is_sqm": false, "sample": 0, "is_caution": false}, "avg": {"value": null, "label": "Median price/sqm (52-week)", "window": "52-week", "is_sqm": true, "sample": 0, "is_caution": false}}, "chart": {"x_label": "Year", "y_left_label": "Median price ($)", "y_right_label": "Sales volume", "primary_field": "median_price", "data": [{"year": 2004, "sales_count": 1, "median_price": 1840000, "avg_price": 1840000, "median_sqm": null, "avg_sqm": null}, {"year": 2011, "sales_count": 1, "median_price": 2305000, "avg_price": 2305000, "median_sqm": 15184.45, "avg_sqm": 15184.45}, {"year": 2012, "sales_count": 1, "median_price": 4000000, "avg_price": 4000000, "median_sqm": 16652.79, "avg_sqm": 16652.79}], "ytd": null, "note": "3 years of qualifying data"}, "price_performance": {"is_sqm_basis": false, "3m": {"nominal": null, "pct": null, "note": "rolling quarter vs same quarter prior year"}, "12m": {"nominal": null, "pct": null}, "3y": {"nominal": null, "pct": null}, "5y": {"nominal": null, "pct": null}, "10y": {"nominal": null, "pct": null}, "20y": {"nominal": null, "pct": null}, "as_of": "2025-12-24"}}}, "data_coverage": {"first_year": 2000, "last_year": 2025, "years": 26}}, "Vacant Land": {"tiles": {"sales_count": {"value": 0, "label": "Sales This Week", "window": null, "sample": 0, "is_caution": false}, "median": {"value": null, "label": "Median price (52-week)", "window": "52-week", "is_sqm": false, "sample": 0, "is_caution": false}, "avg": {"value": null, "label": "Median price/sqm (52-week)", "window": "52-week", "is_sqm": true, "sample": 0, "is_caution": false}}, "chart": {"x_label": "Year", "y_left_label": "Median $/sqm", "y_right_label": "Sales volume", "primary_field": "median_sqm", "data": [{"year": 2002, "sales_count": 2, "median_price": 698750, "avg_price": 698750, "median_sqm": null, "avg_sqm": null}, {"year": 2004, "sales_count": 4, "median_price": 348000, "avg_price": 462750, "median_sqm": null, "avg_sqm": null}, {"year": 2005, "sales_count": 6, "median_price": 271250, "avg_price": 262917, "median_sqm": null, "avg_sqm": null}, {"year": 2006, "sales_count": 8, "median_price": 631000, "avg_price": 1374875, "median_sqm": 8057.07, "avg_sqm": 8057.07}, {"year": 2007, "sales_count": 5, "median_price": 345000, "avg_price": 457940, "median_sqm": 9572.9, "avg_sqm": 9572.9}, {"year": 2009, "sales_count": 1, "median_price": 25600, "avg_price": 25600, "median_sqm": 412.9, "avg_sqm": 412.9}, {"year": 2010, "sales_count": 2, "median_price": 292500, "avg_price": 292500, "median_sqm": 306.8, "avg_sqm": 306.8}, {"year": 2011, "sales_count": 1, "median_price": 255800, "avg_price": 255800, "median_sqm": null, "avg_sqm": null}, {"year": 2012, "sales_count": 1, "median_price": 60000, "avg_price": 60000, "median_sqm": null, "avg_sqm": null}, {"year": 2015, "sales_count": 2, "median_price": 190000, "avg_price": 190000, "median_sqm": 241.94, "avg_sqm": 241.94}, {"year": 2017, "sales_count": 1, "median_price": 1020000, "avg_price": 1020000, "median_sqm": null, "avg_sqm": null}], "ytd": null, "note": null}, "price_performance": {"is_sqm_basis": true, "3m": {"nominal": null, "pct": null, "note": "rolling quarter vs same quarter prior year"}, "12m": {"nominal": null, "pct": null}, "3y": {"nominal": null, "pct": null}, "5y": {"nominal": null, "pct": null}, "10y": {"nominal": null, "pct": null}, "20y": {"nominal": null, "pct": null}, "as_of": "2025-12-24"}, "narrative": ["1 settlements recorded in 2017 with a median price of $1,020,000", "Transaction volume slowed 50% vs 2015 (2 to 1 sales)"], "available_zones": ["Business", "R1", "R2"], "by_zone": {"Business": {"tiles": {"sales_count": {"value": 0, "label": "Sales This Week", "window": null, "sample": 0, "is_caution": false}, "median": {"value": null, "label": "Median price (52-week)", "window": "52-week", "is_sqm": false, "sample": 0, "is_caution": false}, "avg": {"value": null, "label": "Median price/sqm (52-week)", "window": "52-week", "is_sqm": true, "sample": 0, "is_caution": false}}, "chart": {"x_label": "Year", "y_left_label": "Median $/sqm", "y_right_label": "Sales volume", "primary_field": "median_sqm", "data": [{"year": 2006, "sales_count": 1, "median_price": 6545000, "avg_price": 6545000, "median_sqm": 10556.45, "avg_sqm": 10556.45}, {"year": 2007, "sales_count": 1, "median_price": 1300000, "avg_price": 1300000, "median_sqm": 9572.9, "avg_sqm": 9572.9}], "ytd": null, "note": "2 years of qualifying data"}, "price_performance": {"is_sqm_basis": true, "3m": {"nominal": null, "pct": null, "note": "rolling quarter vs same quarter prior year"}, "12m": {"nominal": null, "pct": null}, "3y": {"nominal": null, "pct": null}, "5y": {"nominal": null, "pct": null}, "10y": {"nominal": null, "pct": null}, "20y": {"nominal": null, "pct": null}, "as_of": "2025-12-24"}}, "R1": {"tiles": {"sales_count": {"value": 0, "label": "Sales This Week", "window": null, "sample": 0, "is_caution": false}, "median": {"value": null, "label": "Median price (52-week)", "window": "52-week", "is_sqm": false, "sample": 0, "is_caution": false}, "avg": {"value": null, "label": "Median price/sqm (52-week)", "window": "52-week", "is_sqm": true, "sample": 0, "is_caution": false}}, "chart": {"x_label": "Year", "y_left_label": "Median $/sqm", "y_right_label": "Sales volume", "primary_field": "median_sqm", "data": [{"year": 2015, "sales_count": 1, "median_price": 15000, "avg_price": 15000, "median_sqm": 241.94, "avg_sqm": 241.94}], "ytd": null, "note": "1 year of qualifying data"}, "price_performance": {"is_sqm_basis": true, "3m": {"nominal": null, "pct": null, "note": "rolling quarter vs same quarter prior year"}, "12m": {"nominal": null, "pct": null}, "3y": {"nominal": null, "pct": null}, "5y": {"nominal": null, "pct": null}, "10y": {"nominal": null, "pct": null}, "20y": {"nominal": null, "pct": null}, "as_of": "2025-12-24"}}, "R2": {"tiles": {"sales_count": {"value": 0, "label": "Sales This Week", "window": null, "sample": 0, "is_caution": false}, "median": {"value": null, "label": "Median price (52-week)", "window": "52-week", "is_sqm": false, "sample": 0, "is_caution": false}, "avg": {"value": null, "label": "Median price/sqm (52-week)", "window": "52-week", "is_sqm": true, "sample": 0, "is_caution": false}}, "chart": {"x_label": "Year", "y_left_label": "Median $/sqm", "y_right_label": "Sales volume", "primary_field": "median_sqm", "data": [{"year": 2006, "sales_count": 1, "median_price": 867000, "avg_price": 867000, "median_sqm": 5557.69, "avg_sqm": 5557.69}, {"year": 2009, "sales_count": 1, "median_price": 25600, "avg_price": 25600, "median_sqm": 412.9, "avg_sqm": 412.9}, {"year": 2010, "sales_count": 1, "median_price": 175000, "avg_price": 175000, "median_sqm": 306.8, "avg_sqm": 306.8}], "ytd": null, "note": "3 years of qualifying data"}, "price_performance": {"is_sqm_basis": true, "3m": {"nominal": null, "pct": null, "note": "rolling quarter vs same quarter prior year"}, "12m": {"nominal": null, "pct": null}, "3y": {"nominal": null, "pct": null}, "5y": {"nominal": null, "pct": null}, "10y": {"nominal": null, "pct": null}, "20y": {"nominal": null, "pct": null}, "as_of": "2025-12-24"}}}, "data_coverage": {"first_year": 2002, "last_year": 2017, "years": 11}}, "Office": {"tiles": {"sales_count": {"value": 0, "label": "Sales This Week", "window": null, "sample": 1, "is_caution": false}, "median": {"value": 215000, "label": "Median price (12-week)", "window": "12-week", "is_sqm": false, "sample": 1, "is_caution": false}, "avg": {"value": null, "label": "Median price/sqm (12-week)", "window": "12-week", "is_sqm": true, "sample": 1, "is_caution": false}}, "chart": {"x_label": "Year", "y_left_label": "Median price ($)", "y_right_label": "Sales volume", "primary_field": "median_price", "data": [{"year": 1999, "sales_count": 1, "median_price": 5000000, "avg_price": 5000000, "median_sqm": 5101.0, "avg_sqm": 5101.0}, {"year": 2002, "sales_count": 1, "median_price": 1430000, "avg_price": 1430000, "median_sqm": 7642.97, "avg_sqm": 7642.97}, {"year": 2007, "sales_count": 4, "median_price": 407000, "avg_price": 467625, "median_sqm": 9760.82, "avg_sqm": 9760.82}, {"year": 2008, "sales_count": 3, "median_price": 340000, "avg_price": 458333, "median_sqm": null, "avg_sqm": null}, {"year": 2009, "sales_count": 5, "median_price": 360000, "avg_price": 423000, "median_sqm": null, "avg_sqm": null}, {"year": 2010, "sales_count": 18, "median_price": 395000, "avg_price": 461338, "median_sqm": 11372.55, "avg_sqm": 11812.83}, {"year": 2011, "sales_count": 10, "median_price": 440000, "avg_price": 399500, "median_sqm": 6407.77, "avg_sqm": 6407.77}, {"year": 2012, "sales_count": 7, "median_price": 510000, "avg_price": 629843, "median_sqm": null, "avg_sqm": null}, {"year": 2013, "sales_count": 1, "median_price": 362000, "avg_price": 362000, "median_sqm": null, "avg_sqm": null}, {"year": 2014, "sales_count": 3, "median_price": 251000, "avg_price": 287000, "median_sqm": null, "avg_sqm": null}, {"year": 2015, "sales_count": 3, "median_price": 280000, "avg_price": 370833, "median_sqm": null, "avg_sqm": null}, {"year": 2016, "sales_count": 7, "median_price": 410000, "avg_price": 439071, "median_sqm": 9463.42, "avg_sqm": 9463.42}, {"year": 2017, "sales_count": 2, "median_price": 714500, "avg_price": 714500, "median_sqm": null, "avg_sqm": null}, {"year": 2018, "sales_count": 1, "median_price": 270000, "avg_price": 270000, "median_sqm": null, "avg_sqm": null}, {"year": 2019, "sales_count": 4, "median_price": 592500, "avg_price": 601250, "median_sqm": null, "avg_sqm": null}, {"year": 2020, "sales_count": 5, "median_price": 416000, "avg_price": 527000, "median_sqm": null, "avg_sqm": null}, {"year": 2021, "sales_count": 1, "median_price": 360000, "avg_price": 360000, "median_sqm": null, "avg_sqm": null}, {"year": 2022, "sales_count": 5, "median_price": 890000, "avg_price": 841200, "median_sqm": 11402.44, "avg_sqm": 11402.44}, {"year": 2023, "sales_count": 2, "median_price": 520000, "avg_price": 520000, "median_sqm": null, "avg_sqm": null}, {"year": 2024, "sales_count": 1, "median_price": 350000, "avg_price": 350000, "median_sqm": null, "avg_sqm": null}, {"year": 2025, "sales_count": 1, "median_price": 215000, "avg_price": 215000, "median_sqm": null, "avg_sqm": null}], "ytd": null, "note": null}, "price_performance": {"is_sqm_basis": false, "3m": {"nominal": null, "pct": null, "note": "rolling quarter vs same quarter prior year"}, "12m": {"nominal": null, "pct": null}, "3y": {"nominal": -730500, "pct": -77.26}, "5y": {"nominal": null, "pct": null}, "10y": {"nominal": -52500, "pct": -19.63}, "20y": {"nominal": null, "pct": null}, "as_of": "2025-12-24"}, "narrative": ["1 settlements recorded in 2025 with a median price of $215,000", "Median price down 38.6% vs 2024", "10-year decline: $-52,500 (-19.6%) since 2015"], "available_zones": ["R2"], "by_zone": {"R2": {"tiles": {"sales_count": {"value": 0, "label": "Sales This Week", "window": null, "sample": 0, "is_caution": false}, "median": {"value": null, "label": "Median price (52-week)", "window": "52-week", "is_sqm": false, "sample": 0, "is_caution": false}, "avg": {"value": null, "label": "Median price/sqm (52-week)", "window": "52-week", "is_sqm": true, "sample": 0, "is_caution": false}}, "chart": {"x_label": "Year", "y_left_label": "Median price ($)", "y_right_label": "Sales volume", "primary_field": "median_price", "data": [{"year": 2002, "sales_count": 1, "median_price": 1430000, "avg_price": 1430000, "median_sqm": 7642.97, "avg_sqm": 7642.97}], "ytd": null, "note": "1 year of qualifying data"}, "price_performance": {"is_sqm_basis": false, "3m": {"nominal": null, "pct": null, "note": "rolling quarter vs same quarter prior year"}, "12m": {"nominal": null, "pct": null}, "3y": {"nominal": null, "pct": null}, "5y": {"nominal": null, "pct": null}, "10y": {"nominal": null, "pct": null}, "20y": {"nominal": null, "pct": null}, "as_of": "2025-12-24"}}}, "data_coverage": {"first_year": 1999, "last_year": 2025, "years": 21}}, "OTHER": {"tiles": {"sales_count": {"value": 0, "label": "Sales This Week", "window": null, "sample": 0, "is_caution": false}, "median": {"value": null, "label": "Median price (52-week)", "window": "52-week", "is_sqm": false, "sample": 0, "is_caution": false}, "avg": {"value": null, "label": "Median price/sqm (52-week)", "window": "52-week", "is_sqm": true, "sample": 0, "is_caution": false}}, "chart": {"x_label": "Year", "y_left_label": "Median price ($)", "y_right_label": "Sales volume", "primary_field": "median_price", "data": [{"year": 2000, "sales_count": 9, "median_price": 314000, "avg_price": 980022, "median_sqm": 1774.11, "avg_sqm": 1774.11}, {"year": 2001, "sales_count": 80, "median_price": 277000, "avg_price": 411856, "median_sqm": 4330.93, "avg_sqm": 4443.93}, {"year": 2002, "sales_count": 13, "median_price": 358000, "avg_price": 534308, "median_sqm": null, "avg_sqm": null}, {"year": 2003, "sales_count": 3, "median_price": 622300, "avg_price": 683767, "median_sqm": null, "avg_sqm": null}, {"year": 2004, "sales_count": 5, "median_price": 234000, "avg_price": 247800, "median_sqm": null, "avg_sqm": null}, {"year": 2005, "sales_count": 1, "median_price": 1700000, "avg_price": 1700000, "median_sqm": null, "avg_sqm": null}, {"year": 2006, "sales_count": 3, "median_price": 1200000, "avg_price": 1756667, "median_sqm": 19642.86, "avg_sqm": 19642.86}, {"year": 2007, "sales_count": 6, "median_price": 330000, "avg_price": 387000, "median_sqm": null, "avg_sqm": null}, {"year": 2008, "sales_count": 5, "median_price": 266000, "avg_price": 3318200, "median_sqm": null, "avg_sqm": null}, {"year": 2009, "sales_count": 5, "median_price": 306375, "avg_price": 458483, "median_sqm": null, "avg_sqm": null}, {"year": 2010, "sales_count": 9, "median_price": 430000, "avg_price": 383435, "median_sqm": null, "avg_sqm": null}, {"year": 2011, "sales_count": 6, "median_price": 325000, "avg_price": 3920417, "median_sqm": 12455.12, "avg_sqm": 12455.12}, {"year": 2012, "sales_count": 7, "median_price": 45000, "avg_price": 155614, "median_sqm": null, "avg_sqm": null}, {"year": 2013, "sales_count": 3, "median_price": 550000, "avg_price": 1333333, "median_sqm": null, "avg_sqm": null}, {"year": 2014, "sales_count": 2, "median_price": 336400, "avg_price": 336400, "median_sqm": 5533.98, "avg_sqm": 5533.98}, {"year": 2015, "sales_count": 3, "median_price": 2000000, "avg_price": 2602500, "median_sqm": 27396.69, "avg_sqm": 27396.69}, {"year": 2016, "sales_count": 1, "median_price": 832000, "avg_price": 832000, "median_sqm": null, "avg_sqm": null}, {"year": 2017, "sales_count": 3, "median_price": 40972, "avg_price": 65324, "median_sqm": null, "avg_sqm": null}, {"year": 2018, "sales_count": 1, "median_price": 585000, "avg_price": 585000, "median_sqm": 11250.0, "avg_sqm": 11250.0}, {"year": 2019, "sales_count": 1, "median_price": 1210000, "avg_price": 1210000, "median_sqm": 10000.0, "avg_sqm": 10000.0}], "ytd": null, "note": null}, "price_performance": {"is_sqm_basis": false, "3m": {"nominal": null, "pct": null, "note": "rolling quarter vs same quarter prior year"}, "12m": {"nominal": null, "pct": null}, "3y": {"nominal": null, "pct": null}, "5y": {"nominal": null, "pct": null}, "10y": {"nominal": null, "pct": null}, "20y": {"nominal": null, "pct": null}, "as_of": "2025-12-24"}, "narrative": ["1 settlements recorded in 2019 with a median price of $1,210,000", "Median price up 106.8% vs 2018"], "available_zones": ["Business", "R2"], "by_zone": {"Business": {"tiles": {"sales_count": {"value": 0, "label": "Sales This Week", "window": null, "sample": 0, "is_caution": false}, "median": {"value": null, "label": "Median price (52-week)", "window": "52-week", "is_sqm": false, "sample": 0, "is_caution": false}, "avg": {"value": null, "label": "Median price/sqm (52-week)", "window": "52-week", "is_sqm": true, "sample": 0, "is_caution": false}}, "chart": {"x_label": "Year", "y_left_label": "Median price ($)", "y_right_label": "Sales volume", "primary_field": "median_price", "data": [{"year": 2001, "sales_count": 1, "median_price": 825000, "avg_price": 825000, "median_sqm": 3077.21, "avg_sqm": 3077.21}, {"year": 2006, "sales_count": 1, "median_price": 3850000, "avg_price": 3850000, "median_sqm": 19642.86, "avg_sqm": 19642.86}, {"year": 2015, "sales_count": 2, "median_price": 3800000, "avg_price": 3800000, "median_sqm": 27396.69, "avg_sqm": 27396.69}], "ytd": null, "note": "3 years of qualifying data"}, "price_performance": {"is_sqm_basis": false, "3m": {"nominal": null, "pct": null, "note": "rolling quarter vs same quarter prior year"}, "12m": {"nominal": null, "pct": null}, "3y": {"nominal": null, "pct": null}, "5y": {"nominal": null, "pct": null}, "10y": {"nominal": null, "pct": null}, "20y": {"nominal": null, "pct": null}, "as_of": "2025-12-24"}}, "R2": {"tiles": {"sales_count": {"value": 0, "label": "Sales This Week", "window": null, "sample": 0, "is_caution": false}, "median": {"value": null, "label": "Median price (52-week)", "window": "52-week", "is_sqm": false, "sample": 0, "is_caution": false}, "avg": {"value": null, "label": "Median price/sqm (52-week)", "window": "52-week", "is_sqm": true, "sample": 0, "is_caution": false}}, "chart": {"x_label": "Year", "y_left_label": "Median price ($)", "y_right_label": "Sales volume", "primary_field": "median_price", "data": [{"year": 2001, "sales_count": 3, "median_price": 725000, "avg_price": 770000, "median_sqm": 4400.0, "avg_sqm": 4899.5}, {"year": 2011, "sales_count": 1, "median_price": 13875000, "avg_price": 13875000, "median_sqm": 12455.12, "avg_sqm": 12455.12}], "ytd": null, "note": "2 years of qualifying data"}, "price_performance": {"is_sqm_basis": false, "3m": {"nominal": null, "pct": null, "note": "rolling quarter vs same quarter prior year"}, "12m": {"nominal": null, "pct": null}, "3y": {"nominal": null, "pct": null}, "5y": {"nominal": null, "pct": null}, "10y": {"nominal": null, "pct": null}, "20y": {"nominal": null, "pct": null}, "as_of": "2025-12-24"}}}, "data_coverage": {"first_year": 2000, "last_year": 2019, "years": 20}}}}